<NotepadPlus>
    <Session activeView="0">
        <mainView activeIndex="7">
            <File firstVisibleLine="0" xOffset="0" scrollWidth="6664210" startPos="1463" endPos="1463" selMode="0" lang="Normal Text" encoding="-1" filename="C:\Users\jdiscar.GUARDIAN\Desktop\BD.txt" />
            <File firstVisibleLine="168" xOffset="0" scrollWidth="6664210" startPos="8476" endPos="8441" selMode="0" lang="Normal Text" encoding="-1" filename="C:\wroot\projects\ga\docs\setup.txt" />
            <File firstVisibleLine="0" xOffset="0" scrollWidth="6664210" startPos="0" endPos="0" selMode="0" lang="Normal Text" encoding="-1" filename="C:\wroot\projects\ga\log\riskengine.log" />
            <File firstVisibleLine="37" xOffset="0" scrollWidth="6664210" startPos="4235" endPos="4235" selMode="0" lang="Java" encoding="-1" filename="C:\wroot\projects\ga\code\v5wire\javautils\src\main\java\com\ga\javautils\cluster\AdHoc.java" />
            <File firstVisibleLine="9" xOffset="0" scrollWidth="8682140" startPos="25" endPos="2052" selMode="0" lang="Java" encoding="-1" filename="C:\Users\jdiscar.GUARDIAN\Downloads\DiscClient.java" />
            <File firstVisibleLine="306" xOffset="0" scrollWidth="6664210" startPos="11470" endPos="11417" selMode="0" lang="XML" encoding="-1" filename="C:\wroot\projects\ga\code\thirdpartysw\jboss-eap-6.2\jboss-as\standalone\configuration\standalone-full.xml" />
            <File firstVisibleLine="1389" xOffset="0" scrollWidth="6664210" startPos="62726" endPos="62726" selMode="0" lang="XML" encoding="-1" filename="C:\wroot\projects\ga\code\doral\customer-data\_models\platform\DIBusiness\FraudMAP_riskeng_model_definition.xml" />
            <File firstVisibleLine="0" xOffset="0" scrollWidth="6664210" startPos="993" endPos="993" selMode="0" lang="Properties" encoding="-1" filename="C:\wroot\projects\ga\code\doral\customer-data\MyNetWatchman\MoneyMoveExport\configuration\thirdparty.properties" />
        </mainView>
        <subView activeIndex="0" />
    </Session>
</NotepadPlus>
